replit_ffmpeg
