Metadata-Version: 2.1
Name: replit-ffmpeg
Version: 0.4
Summary: Installs FFmpeg for you on Replit.
Author: AWeirdDev
Author-email: AWeirdDev <aweirdscratcher@gmail.com>
License: MIT License
Project-URL: Homepage, https://github.com/AWeirdScratcher/replit-ffmpeg
Project-URL: Bug Tracker, https://github.com/AWeirdScratcher/replit-ffmpeg/issues
Keywords: replit,ffmpeg,opus,youtube-dl
Classifier: Programming Language :: Python :: 3.9
Classifier: License :: OSI Approved :: MIT License
Classifier: Operating System :: OS Independent
Requires-Python: >=3.9
License-File: LICENSE
